Workbook

Sheet Financial Ratios
B1: Ratio | C1: FY1400 (ended Mar 2022) | D1: FY1401 (ended Mar 2023) | E1: FY1402 (ended Mar 2024) | G1: DuPont analysis (ROE = Net income / Equity) | H1: ='Income Statement'!C15/'Balance Sheet'!C36 -> 0.24885956 | I1: ='Income Statement'!D15/'Balance Sheet'!D36 -> 0.28214708 | J1: ='Income Statement'!E15/'Balance Sheet'!E36 -> 0.41376744
B2: Gross profit margin (TTM) | C2: 0.045329558 | D2: 0.045139029 | E2: 0.094299011 | G2: Tracking the DuPont ratios into next year lets us estimate and forecast the trend in profitability and the growth of debt.
B3: Operating profit margin (TTM) | C3: -0.08543549 | D3: -0.021713248 | E3: 0.15788808 | G3: The company has the lowest ROE among its peers, which is a clear weakness.
B4: Pre-tax profit margin | C4: 0.0037915467 | D4: 0.053681909 | E4: 0.28410258 | G4: Based on the DuPont analysis, the company is not an attractive investment.
B5: Net profit margin (TTM) | C5: ='Income Statement'!C15/'Income Statement'!C2 -> 0.079466043 | D5: ='Income Statement'!D15/'Income Statement'!D2 -> 0.072498085 | E5: ='Income Statement'!E15/'Income Statement'!E2 -> 0.11861256
B6: Return on assets (ROA) | C6: ='Income Statement'!C15/'Balance Sheet'!C16 -> 0.037892595 | D6: ='Income Statement'!D15/'Balance Sheet'!D16 -> 0.035758937 | E6: ='Income Statement'!E15/'Balance Sheet'!E16 -> 0.061936667
B7: Return on equity (ROE) | C7: 0.18972896 | D7: 0.0043995135 | E7: 0.12281319
B8: EBIT / Total assets | C8: 0.054795327 | D8: -0.026864658 | E8: -0.0084295018
B9: Asset turnover | C9: 0.38719631 | D9: 0.31444378 | E9: 0.3882193 | G9: Beta calculation
B10: Fixed asset turnover | C10: 0.77749197 | D10: 0.62079808 | E10: 0.74052265 | H10: Akhaber (TCI) | I10: Hamrah (MCI) | J10: Asiatech
B11: Receivables turnover | C11: 1.1346003 | D11: 0.93161552 | E11: 1.3366772 | G11: 1-year stock return | H11: 0.47 | I11: 0.55 | J11: 0.055
B12: Days sales outstanding (days) | C12: 391.79253 | D12: 273.06519 | E12: 266.62384 | G12: 1-year market (TSE index) return | H12: 0.48 | I12: 0.48 | J12: 0.48
B13: Total liabilities / Total assets | C13: 0.68371053 | D13: 0.7727491 | E13: 0.85399926 | G13: Risk-free rate | H13: 0.35 | I13: 0.35 | J13: 0.35
B14: Total liabilities / Equity | C14: 2.1616607 | D14: 3.4004227 | E14: 5.8492803 | G14: Stock beta | H14: =(H11-H13)/(H12-H13) -> 0.92307692 | I14: =(I11-I13)/(I12-I13) -> 1.5384615 | J14: 0.57
B15: Debt ratio | C15: 0.19297068 | D15: 0.16545836 | E15: 0.22484033
B16: Debt / Equity | C16: 0.84915255 | D16: 1.1332707 | E16: 1.0023041
B17: Long-term debt ratio | C17: 0.023317894 | D17: 0 | E17: 0 | G17: Break-even analysis (latest year, FY1402)
B18: Retained earnings / Total assets | C18: 0.081638321 | D18: 0.0017766469 | E18: -0.047287886 | G18: Operating break-even | H18: ='Income Statement'!E7/'Financial Ratios'!H19 -> 41990622
B19: Interest coverage ratio | C19: 4.2423968 | G19: Degree of operating leverage (DOL) | H19: =(('Income Statement'!E7-'Income Statement'!D7)/'Income Statement'!D7)/(('Income Statement'!E2-'Income Statement'!D2)/'Income Statement'!D2) -> 2.0477456
B20: Current ratio | C20: 0.85753247 | D20: 0.61001532 | E20: 0.56527459 | G20: Financial break-even | H20: =-'Income Statement'!E8/0.8 -> 48092535
B21: Quick ratio | C21: 0.85094951 | D21: 0.605694 | E21: 0.56111885 | G21: Degree of financial leverage (DFL) | H21: =(('Income Statement'!E15-'Income Statement'!D15)/'Income Statement'!D15)/(('Income Statement'!E7-'Income Statement'!D7)/'Income Statement'!D7) -> 1.6204005
B22: Cash ratio | C22: 0.088747572 | D22: 0.11413509 | E22: 0.076036054 | G22: Total break-even | H22: =H20+H18 -> 90083157
B23: Free cash flow to firm / Revenue | C23: 0.2126899 | D23: 0.071694618 | E23: 0.11004458 | G23: Degree of total leverage (DTL) | H23: =H21*H19 -> 3.3181679
B24: Free cash flow to firm / Net income | C24: 1.1783681 | D24: 18.909069 | E24: 2.0499379
B25: Free cash flow to equity / Revenue | C25: 0.17796396 | D25: 0.17991057 | E25: 0.0095119146 | G25: Leverage degrees are computed from year-over-year percentage changes (FY1401 to FY1402).
B26: Free cash flow to equity / Net income | C26: 0.98597555 | D26: 47.450444 | E26: 0.17719032
B27: Capital expenditure / Revenue | C27: 0.20292381 | D27: 0.27237485 | E27: 0.11583696
B28: Capital expenditure / Net income | C28: 1.1242609 | D28: 71.837397 | E28: 2.1578398
B29: Operating cash flow / Revenue | C29: 0.066924384 | D29: 0.12253462 | E29: 0.069935176
B30: Operating cash flow / Total liabilities | C30: 0.041024258 | D30: 0.052852907 | E30: 0.032698912
B31: Financing cash flow / Revenue | C31: 0.032467802 | D31: -0.13393349 | E31: 0.12779078
B32: Investing cash flow / Revenue | C32: -0.078867393 | D32: 0.044371578 | E32: -0.12869322
B34: Valuation (billion IRR) | C34: FY1400 (ended Mar 2022) | D34: FY1401 (ended Mar 2023) | E34: FY1402 (ended Mar 2024)
B35: Enterprise value | C35: 434507.07 | D35: 543969.83 | E35: 697388.32
B36: Book value | C36: 70287.938 | D36: 68005.838 | E36: 91990.937
B37: Operating cash flow | C37: 6407.123 | D37: 10887.268 | E37: 8481.694
B38: Free cash flow to firm (FCFF) | C38: 20362.24 | D38: 6370.106 | E38: 13346.137
B39: Free cash flow to equity (FCFE) | C39: 17037.691 | D39: 15985.153 | E39: 1153.599
A66: *

Sheet Peer Comparison
B2: Ticker | C2: P/E | D2: P/D | E2: P/B | F2: P/S | G2: P/FCFE | H2: EPS
B3: Hamrah (MCI) | C3: 6.5954774 | D3: 9.776536 | E3: 2.586363 | F3: 0.662592 | G3: 4.737813 | H3: 796.05
B4: Akhaber (TCI) | C4: 10.95082 | D4: 30.208171 | E4: 0.639087 | F4: 3.877209 | G4: 55.720989 | H4: 44.98
B5: Asiatech | C5: 4.6960409 | D5: 31.458777 | E5: 2.093469 | F5: 1.014455 | G5: 14.891679 | H5: 648.72
C6: P/E: Asiatech looks the most undervalued of the three. Looking further into each company's expansion plans would show whether market demand for Akhaber is justified, or whether its high P/E simply comes from its low net income. | D6: P/D: For an investor who values dividends, Hamrah-e Aval is the best choice, since it pays higher dividends than the other two. | E6: P/B: Below 1 for Akhaber. This may come from its recent large capital increase, or from the market ignoring how cheap it is. P/E suggested the opposite, but this confirms that the high P/E is due to low earnings. | F6: P/S: Very favourable for Hamrah and Asiatech, meaning a small change in margin has a large effect on their profitability. For Akhaber it is close to 4, which is high for this industry. | G6: P/FCFE: Hamrah is by far the best value thanks to its strong free cash flow. On this ratio too, Akhaber does not look like a good investment. | H6: EPS: Latest earnings per share. Akhaber's EPS is far lower than the other two, which clearly explains its high P/E.

Sheet Income Statement
B1: Fiscal period (million IRR) | C1: FY1400 (ended Mar 2022) | D1: FY1401 (ended Mar 2023) | E1: FY1402 (ended Mar 2024)
B2: Operating revenue | C2: 368170477 | D2: 487219107 | E2: 671459971
B3: Cost of revenue | C3: -282741912 | D3: -376094229 | E3: -515609104
B4: Gross profit | C4: 85428565 | D4: 111124878 | E4: 155850867
B5: General & administrative expenses | C5: -60296298 | D5: -72109023 | E5: -89565319
B6: Other operating income (expense), net | C6: 2883783 | D6: 9444754 | E6: 19700564
B7: Operating profit (EBIT) | C7: 28016050 | D7: 48460609 | E7: 85986112
B8: Finance costs | C8: -14920002 | D8: -23976818 | E8: -38474028
B9: Other non-operating income (expense), net | C9: 30161801 | D9: 25406363 | E9: 56113904
B10: Profit before share of associates | C10: 43257849 | D10: 49890154 | E10: 103625988
B11: Share of profit of associates | C11: 0 | D11: -13553 | E11: 127801
B12: Profit before tax (continuing operations) | C12: 43257849 | D12: 49876601 | E12: 103753789
B13: Income tax | C13: -14000798 | D13: -14554149 | E13: -24110204
... B18: Earnings per share, after tax (IRR) | C18: 488 | D18: 589 | E18: 1327

Sheet Balance Sheet
B1: Fiscal period (million IRR) | C1: FY1400 (ended Mar 2022) | D1: FY1401 (ended Mar 2023) | E1: FY1402 (ended Mar 2024)
B2: Assets
B3: Cash | C3: 19944212 | D3: 42780455 | E3: 63925172
B4: Short-term investments | C4: 38203181 | D4: 35076707 | E4: 62560316
B5: Inventories | C5: 6336289 | D5: 12783186 | E5: 29928551
B6: Prepayments | C6: 19529172 | D6: 35300090 | E6: 40252855
B7: Assets held for sale | C7: 159097 | D7: 96166 | E7: 3864505
B8: Total current assets | C8: 185826246 | D8: 264574426 | E8: 348317238
B9: Long-term trade receivables | C9: 2043096 | D9: 1110669 | E9: 826587
B10: Long-term investments | C10: 5900188 | D10: 10705348 | E10: 6797232
B11: Property, plant & equipment | C11: 523909953 | D11: 652509742 | E11: 862133173
B12: Intangible assets | C12: 11083027 | D12: 9814352 | E12: 9451915
B13: Goodwill | C13: 466597 | D13: 430819 | E13: 401215
B14: Other assets | C14: 41812404 | D14: 45871922 | E14: 50029966
... B16: Total assets | C16: 772104714 | D16: 987793686 | E16: 1285887481
B17: Liabilities
B18: Advances from customers | C18: 24201709 | D18: 31144582 | E18: 28353233
B19: Income tax provision | C19: 20372540 | D19: 25058384 | E19: 34547152
B20: Dividends payable | C20: 19173284 | D20: 14606548 | E20: 8386419
B21: Current portion of borrowings | C21: 150429121 | D21: 193373076 | E21: 220075154
B22: Total current liabilities | C22: 565096030 | D22: 770699472 | E22: 787506562
B23: Long-term payables | C23: 52102417 | D23: 46881539 | E23: 215268702
B24: Long-term borrowings | C24: 0 | D24: 0 | E24: 36984931
B25: Employee end-of-service benefits | C25: 37341761 | D25: 45021047 | E25: 53643350
B26: Total non-current liabilities | C26: 89444178 | D26: 91902586 | E26: 305896983
B27: Total liabilities | C27: 654540208 | D27: 862602058 | E27: 1093403545
B28: Equity
B29: Share capital | C29: 60000000 | D29: 60000000 | E29: 60000000
B30: Treasury shares | C30: 0 | D30: -1032188 | E30: -9720504
B31: Legal reserve | C31: 11557539 | D31: 13907092 | E31: 17154008
B32: Development reserve | C32: 3287379 | D32: 3287379 | E32: 26239379
B33: Retained earnings (deficit) | C33: 37935167 | D33: 41721844 | E33: 90081387
B34: Equity attributable to owners of the parent | C34: 106471797 | D34: - | E34: -
B35: Minority interest | C35: 11092709 | D35: - | E35: -
B36: Total equity | C36: 117564506 | D36: 125191628 | E36: 192483936
B37: Total liabilities & equity | C37: 772104714 | D37: 987793686 | E37: 1285887481

Sheet Revenue by Service
B1: Service (million IRR) | C1: Contract date | D1: FY1399 (ended Mar 2021) | E1: FY1400 (ended Mar 2022) | F1: FY1401 (ended Mar 2023) | G1: FY1402 (ended Mar 2024) | H1: FY1403 (ended Mar 2025)
B2: Other income | C2: 1403-01 | D2: 654743 | E2: 707200 | F2: 198680 | G2: 402450 | H2: 334181
B3: Telecom service usage fees | C3: 1403-01 | D3: 4816967 | E3: 5083693 | F3: 5217524 | G3: 2945667 | H3: 797031
B4: Telecom services (voice) | D4: 15482845 | E4: 13780190 | F4: - | G4: - | H4: -
B5: Telecom services (data) | D5: 35084314 | E5: 49933406 | F5: - | G5: - | H5: -
B6: Other operating revenue: minimum monthly landline charge | C6: 1403-01 | D6: - | E6: - | F6: 19518039 | G6: 32089198 | H6: 28677369
B7: Telecom services (data) | C7: 1403-01 | D7: - | E7: - | F7: 53079451 | G7: 61075388 | H7: 77636426
B8: Telecom services (voice) | C8: 1403-01 | D8: - | E8: - | F8: 9714171 | G8: 12214569 | H8: 14417123
B9: Maintenance & contracting | D9: - | E9: - | F9: 8708281 | G9: 10281500 | H9: 17634620
B10: Access services | D10: - | E10: - | F10: 3300969 | G10: 7736880 | H10: 23022937
B11: Power & space (colocation) | D11: - | E11: - | F11: 8947235 | G11: 12772095 | H11: 18851889
B12: Transmission line leasing | D12: - | E12: - | F12: 17983227 | G12: 23088572 | H12: 29800488
B13: Facilities & services provided to MCI (Hamrah-e Aval) | D13: 18213835 | E13: 21330773 | F13: - | G13: - | H13: -
B14: Use of company facilities | D14: 2292767 | E14: 1501421 | F14: - | G14: - | H14: -
B15: After-sales services | D15: 548905 | E15: 602249 | F15: - | G15: - | H15: -
B16: Other operating revenue | D16: 2612819 | E16: 4698635 | F16: 6782285 | G16: 13079056 | H16: 17695109
B17: Total | D17: =SUM(D2:D16) -> 79707195 | E17: =SUM(E2:E16) -> 97637567 | F17: =SUM(F2:F16) -> 133449862 | G17: =SUM(G2:G16) -> 175685375 | H17: =SUM(H2:H16) -> 228867173

Sheet Shareholders
A1: Shareholder | B1: Number of shares | C1: Ownership (%)
A2: Tose'e Etemad Mobin Co. | B2: 414683000000 | C2: 43.1
A3: Government of Iran | B3: 189848000000 | C3: 19.7
A4: Vaset Mali Shahrivar Panjom Co. | B4: 37638000000 | C4: 3.9
A5: Mobile Communication Company of Iran (MCI) | B5: 20881000000 | C5: 2.1
A6: Tehran Province Investment Co. | B6: 11036000000 | C6: 1.1
A7: Justice Shares Co. of Khorasan Razavi Province | B7: 10646000000 | C7: 1.1
A8: Other shareholders | B8: =B9-SUBTOTAL(109,B2:B7) -> 2.7740953e+11 | C8: =100-SUBTOTAL(109,C2:C7) -> 29
B9: =B2/C2*100 -> 9.6214153e+11 | C9: 100
